logs_analyzer/__init__.py
logs_analyzer/lib.py
logs_analyzer/settings.py
logs_analyzer/validators.py
logs_analyzer-0.5.2.dist-info/LICENSE
logs_analyzer-0.5.2.dist-info/METADATA
logs_analyzer-0.5.2.dist-info/WHEEL
logs_analyzer-0.5.2.dist-info/top_level.txt
logs_analyzer-0.5.2.dist-info/RECORD
