Metadata-Version: 2.1
Name: logs-analyzer
Version: 0.5.2
Summary: Logs-analyzer is a library containing functions that can help you extract usable data from logs.
Home-page: https://github.com/ddalu5/logs-analyzer
Author: Salah OSFOR
Author-email: osfor.salah@gmail.com
License: Apache V2
Platform: UNKNOWN
Classifier: Intended Audience :: Developers
Classifier: Intended Audience :: System Administrators
Classifier: Intended Audience :: Information Technology
Classifier: Topic :: System :: Logging
Classifier: Topic :: System :: Monitoring
Classifier: Programming Language :: Python :: 2.7
Classifier: Programming Language :: Python :: 3.6
Classifier: Programming Language :: Python :: 3.7
